{"cameraMode":{"drawMode":0,"name":"Shaded","section":"Shading Mode"},"sceneLighting":true,"audioPlay":false,"sceneViewState":{"m_AlwaysRefresh":true,"showFog":true,"showSkybox":true,"showFlares":true,"showImageEffects":true,"showParticleSystems":true,"showVisualEffectGraphs":true,"m_FxEnabled":true},"in2DMode":false,"pivot":{"x":0.7260456085205078,"y":1.6469287872314454,"z":-1.6444168090820313},"rotation":{"x":-0.06261336803436279,"y":0.9241493940353394,"z":-0.1727631390094757,"w":-0.33493319153785708},"size":10.0,"orthographic":false}